Ioana_project/__init__.py
Ioana_project/ioana.py
Ioana_first_project-0.1.2.dist-info/METADATA
Ioana_first_project-0.1.2.dist-info/WHEEL
Ioana_first_project-0.1.2.dist-info/top_level.txt
Ioana_first_project-0.1.2.dist-info/RECORD
