Metadata-Version: 2.1
Name: Ioana-first-project
Version: 0.1.2
Summary: first project
Home-page: UNKNOWN
Author: Scheul-Ioana
Author-email: ioana.scheul@yahoo.com
License: UNKNOWN
Platform: UNKNOWN
